stargaze_protobuf/__init__.py
stargaze_protobuf/__init__.pyi
stargaze_protobuf/proofs.proto
stargaze_protobuf/proofs_pb2.py
stargaze_protobuf/proofs_pb2.pyi
stargaze_protobuf/cosmos/__init__.py
stargaze_protobuf/cosmos/__init__.pyi
stargaze_protobuf/cosmos/auth/__init__.py
stargaze_protobuf/cosmos/auth/__init__.pyi
stargaze_protobuf/cosmos/auth/v1beta1/__init__.py
stargaze_protobuf/cosmos/auth/v1beta1/__init__.pyi
stargaze_protobuf/cosmos/auth/v1beta1/auth.proto
stargaze_protobuf/cosmos/auth/v1beta1/auth_pb2.py
stargaze_protobuf/cosmos/auth/v1beta1/auth_pb2.pyi
stargaze_protobuf/cosmos/auth/v1beta1/genesis.proto
stargaze_protobuf/cosmos/auth/v1beta1/genesis_pb2.py
stargaze_protobuf/cosmos/auth/v1beta1/genesis_pb2.pyi
stargaze_protobuf/cosmos/auth/v1beta1/query.proto
stargaze_protobuf/cosmos/auth/v1beta1/query_pb2.py
stargaze_protobuf/cosmos/auth/v1beta1/query_pb2.pyi
stargaze_protobuf/cosmos/auth/v1beta1/query_pb2_grpc.py
stargaze_protobuf/cosmos/authz/__init__.py
stargaze_protobuf/cosmos/authz/__init__.pyi
stargaze_protobuf/cosmos/authz/v1beta1/__init__.py
stargaze_protobuf/cosmos/authz/v1beta1/__init__.pyi
stargaze_protobuf/cosmos/authz/v1beta1/authz.proto
stargaze_protobuf/cosmos/authz/v1beta1/authz_pb2.py
stargaze_protobuf/cosmos/authz/v1beta1/authz_pb2.pyi
stargaze_protobuf/cosmos/authz/v1beta1/event.proto
stargaze_protobuf/cosmos/authz/v1beta1/event_pb2.py
stargaze_protobuf/cosmos/authz/v1beta1/event_pb2.pyi
stargaze_protobuf/cosmos/authz/v1beta1/genesis.proto
stargaze_protobuf/cosmos/authz/v1beta1/genesis_pb2.py
stargaze_protobuf/cosmos/authz/v1beta1/genesis_pb2.pyi
stargaze_protobuf/cosmos/authz/v1beta1/query.proto
stargaze_protobuf/cosmos/authz/v1beta1/query_pb2.py
stargaze_protobuf/cosmos/authz/v1beta1/query_pb2.pyi
stargaze_protobuf/cosmos/authz/v1beta1/query_pb2_grpc.py
stargaze_protobuf/cosmos/authz/v1beta1/tx.proto
stargaze_protobuf/cosmos/authz/v1beta1/tx_pb2.py
stargaze_protobuf/cosmos/authz/v1beta1/tx_pb2.pyi
stargaze_protobuf-0.1.0.dist-info/METADATA
stargaze_protobuf-0.1.0.dist-info/WHEEL
stargaze_protobuf-0.1.0.dist-info/RECORD
